botchain/__init__.py
botchain/attachment.py
botchain/main.py
botchain/strings.py
botchain/utils.py
botchain-0.0.2.dist-info/METADATA
botchain-0.0.2.dist-info/WHEEL
botchain-0.0.2.dist-info/top_level.txt
botchain-0.0.2.dist-info/RECORD
